{
  "company_key": "baumer electric ag",
  "company_name": "Baumer Electric AG",
  "domain": "www.baumer-lernende.ch",
  "domain_url": "https://www.baumer-lernende.ch",
  "events": "MSV 2025 Full Exhibitor List",
  "event_count": 1,
  "lead_class": "whitespace",
  "matched_account_id": null,
  "enrichment": {
    "company_name": "Baumer Electric AG",
    "opportunity_score": 24,
    "estimated_deal_eur": 2200,
    "primary_segment": "unknown",
    "size_tier": "small",
    "timing_signals": [],
    "fit_score": 0.2,
    "component_scores": {
      "size": 0.3,
      "revenue": 0.2,
      "nace_fit": 0.2,
      "event_relevance": 0.25,
      "signals": 0.0,
      "client_bonus": 0.5
    },
    "ares_done": true,
    "ares_error": "Not found in ARES",
    "is_client": true,
    "current_products": "AutoCAD LT",
    "total_seats": "1",
    "current_acv_eur": "500.0",
    "potential_acv_eur": "9400.0",
    "nearest_renewal": "2026-09-03",
    "days_to_renewal": "133",
    "top_upsell": "AEC Collection",
    "top_upsell_reason": "Bundle with Revit, Civil 3D, Navisworks for full AEC workflow",
    "all_upsells": "AEC Collection; PDMC; AutoCAD (full)",
    "maturity_label": "Entry",
    "industry_segment": "Construction Services",
    "ml_domain": "www.comelectric.cz",
    "zi_done": true,
    "employee_count": 31,
    "revenue": 2731,
    "zi_company_name": "Baumer Electric",
    "zi_domain": "www.baumer-lernende.ch",
    "zi_city": "Frauenfeld",
    "zi_country": "Switzerland",
    "zi_industry": "",
    "zi_sub_industry": ""
  },
  "website_data": {
    "success": true,
    "domain": "https://www.baumer-lernende.ch",
    "homepage": {
      "title": "Berufsbildung Baumer Electric AG | Baumer Trainees",
      "description": "",
      "text_excerpt": "Berufsbildung Baumer Electric AG | Baumer Trainees\nUnsere Berufsbildner\nMit modernen Ausbildungsmethoden und engagierten, erfahrenen Berufsbildenden sorgt Baumer dafür, dass du bestens auf deine berufliche Zukunft vorbereitet bist!\nMore details\nUnsere Ausbildungsberufe\nBei Baumer investieren wir in die Zukunft – deine Zukunft! Starte deine Karriere mit einer spannenden Ausbildung in einem unserer vielseitigen Lehrberufe. Wir begleiten dich auf deinem Weg und unterstützen dich dabei, dein Potenzial voll auszuschöpfen!\nMore details\nOhne Nachwuchs keine Zukunft – Deine Karriere in der Welt der Sensoren!\nSensoren sind die Grundlage moderner Technologie: Sie steuern Maschinen, helfen Robotern bei präzisen Aufgaben und machen die Industrie von morgen möglich. Bei der\nBaumer Electric AG\nentwickeln und produzieren wir diese Hightech-Produkte – und du kannst ein Teil davon werden!\nMit über\n50 Lernenden\nbieten wir eine\nerstklassige Ausbildung\nin vielen spannenden Berufen. Egal, ob du technisch, kreativ oder organisatorisch interessiert bist – bei uns findest du deinen Weg:\nElektroniker/in EFZ\nDie ersten zwei Lehrjahre verbringst du in unserer modernen Lehrwerkstatt und erwirbst fundiertes Wissen. Danach setzt du es in Projekten ein und arbeitest direkt an unseren Sensoren.\nInformatiker/in EFZ\nFachrichtung Applikationsentwicklung\nVerwirkliche eigene Ideen in Software. Von der ersten Zeile Code bis zur fertigen Anwendung begleitest du den gesamten Entwicklungsprozess.\nInformatiker/in EFZ\nFachrichtung Plattformentwicklung\nStelle sicher, dass unsere IT-Systeme reibungslos funktionieren, betreue Netzwerke und unterstütze unsere Teams bei technischen Herausforderungen.\nKauffrau/Kaufmann EFZ\nPlane, organisiere und unterstütze die Abläufe hinter unseren Projekten.\nKonstrukteur/in EFZ\nEntwirf Bauteile und Gehäuse, die unsere Sensoren robust und leistungsstark machen.\nLogistiker/in EFZ\nStelle sicher, dass unsere Sensoren zur richtigen Zeit am richtigen Ort ankommen.\nMediamatiker/in EFZ\nSetze kreative Ideen um, entwickle Websites, Videos und digitale Inhalte, um unsere Produkte ins richtige Licht zu rücken.\nPolymechaniker/in EFZ\nArbeite an Maschinen, die unsere Sensoren herstellen und sorge dafür, dass sie optimal laufen.\nBei uns arbeitest du nicht nur mit modernster Technik, sondern auch an Projekten, die die Zukunft gestalten. Ob du kreativ, technisch oder organisatorisch bist – wir fördern deine Talente und machen dich fit für die Berufswelt.\nEntdecke deine Möglichkeiten und starte deine Ausbildung bei der\nBaumer Electric AG\n– gemeinsam schaffen wir die Technik von morgen!\nBeruf kennenlernen\nUnsere Benefits\nBei uns in der Lehre erhälst du nicht nur einen tollen Lohn und entsprechende Goodies, sondern noch vieles mehr. Hier eine Auswahl unseres Angebotes:\nÜber 50 Lernende in 8 verschiedenen Lehrberufen\nAttraktive Löhne (inklusive 13. Monatslohn) sowie CHF 500 für einen Laptop\nBezahlte Lehrmittel für die Berufsfachschule\nErhalt des Ostwindabo während der ganzen Lehr"
    },
    "about": {},
    "products": {},
    "contact_page": {
      "url": "https://www.baumer-lernende.ch/contact",
      "text": "Contact | Baumer Trainees\nContact\nContact\nCause for inquiry *\nplease select\nCompany\nAusbildungsberufe\nLehrstellen\nDiverses\nMessage *\nMrs.\nMr.\nFirst name *\nFamily name *\nE-Mail *\nPhone *\nPlease always enter your telephone number with the country code, e.g. +49 or 0049.\nCompany *\nStreet, No *\nPostcode *\nCity *\nCountry *\n_Serbia and Montenegro\n*No preferential origin*\nAfghanistan\nAland Islands\nAlbania\nAlgeria\nAmer.Virgin Is.\nAndorra\nAngola\nAnguilla\nAntarctica\nAntigua/Barbuda\nArgentina\nArmenia\nAruba\nAustralia\nAustria\nAzerbaijan\nBahamas\nBahrain\nBangladesh\nBarbados\nBELARUS\nBelgium\nBelize\nBenin\nBermuda\nBhutan\nBolivia\nBosnia-Herz.\nBotswana\nBouvet Island\nBrazil\nBrit.Ind.Oc.Ter\nBrit.Virgin Is.\nBrunei Dar-es-S\nBulgaria\nBurkina-Faso\nBurundi\nCambodia\nCameroon\nCanada\nCanary Islands\nCape Verdian\nCayman Islands\nCentr.Afr.Rep.\nChad\nChile\nChina\nChristmas Islnd\nCocos Islands\nColombia\nComorin\nCongo\nCook Islands\nCosta Rica\nCroatia\nCuba\nCyprus\nCzech Republic\nDemocratic Republic of the Congo\nDenmark\nDjibouti\nDominica\nDominican Rep.\nDutch Antilles\nDutch Antilles\nDutch Antilles\nDutch Antilles\nEast bank\nEast Timor\nEast Timor\nEcuador\nEgypt\nEl Salvador\nEquatorial Gui.\nEritrea\nEstonia\nEthiopia\nFalkland Islnds\nFaroe Islands\nFiji\nFinland\nFrance\nFrenc.Polynesia\nFrench Guinea\nFrench S.Territ\nGabon\nGambia\nGeorgia\nGermany\nGhana\nGibraltar\nGreat Britain\nGreece\nGreenland\nGrenada\nGuadeloupe\nGuam\nGuatemala\nGuernsey\nGuinea\nGuinea-Bissau\nGuyana\nHaiti\nHeard/McDon.Isl\nHonduras\nHong Kong\nHungary\nIceland\nIndia\nIndonesia\nInternational\nIran\nIraq\nIreland\nIsle of Man\nIsrael\nItaly\nIvory Coast\nJamaica\nJapan\nJersey\nJordan\nKasachstan\nKenya\nKirghistan\nKiribati\nKosovo\nKuwait\nLaos\nLatvia\nLebanon\nLesotho\nLiberia\nLibya\nLiechtenstein\nLithuania\nLuxembourg\nMacau\nMadagascar\nMalawi\nMalaysia\nMaldives\nMali\nMalta\nMarshall Islnds\nMartinique\nMauretania\nMauritius\nMayotte\nMexico\nMicronesia\nMinor Outl.Ins.\nMoldavia\nMonaco\nMongolia\nMontenegro\nMontserrat\nMorocco\nMozambique\nMyanmar\nN.Mariana Islnd\nNamibia\nNauru\nNepal\nNetherlands\nNew Caledo"
    }
  },
  "technographics": {
    "success": true,
    "company": "Baumer Electric AG",
    "autodesk_products": [],
    "competitor_products": [],
    "cad_bim_other": [],
    "total_technologies": 12,
    "all_technologies": [
      {
        "product": "Cloudflare",
        "vendor": "Cloudflare, Inc.",
        "category": "Other IT Infrastructure Software",
        "categoryParent": "IT Infrastructure"
      },
      {
        "product": "CSS",
        "vendor": "World Wide Web Consortium",
        "category": "Programming Languages",
        "categoryParent": "Programming"
      },
      {
        "product": "Modernizr",
        "vendor": "Modernizr",
        "category": "Frameworks and Libraries",
        "categoryParent": "Programming"
      },
      {
        "product": "jQuery",
        "vendor": "The jQuery Foundation Inc",
        "category": "Frameworks and Libraries",
        "categoryParent": "Programming"
      },
      {
        "product": "Font Awesome",
        "vendor": "Fonticons, Inc.",
        "category": "Other Web Tools and Plugins",
        "categoryParent": "Web Tools and Plugins"
      },
      {
        "product": "JQuery 1.11.1",
        "vendor": "The jQuery Foundation Inc",
        "category": "Frameworks and Libraries",
        "categoryParent": "Programming"
      },
      {
        "product": "Bootstrap",
        "vendor": "Twitter, Inc.",
        "category": "Frameworks and Libraries",
        "categoryParent": "Programming"
      },
      {
        "product": "CAPTCHA (common)",
        "vendor": "",
        "category": "CAPTCHA",
        "categoryParent": "Web Tools and Plugins"
      },
      {
        "product": "reCAPTCHA",
        "vendor": "Google LLC",
        "category": "CAPTCHA",
        "categoryParent": "Web Tools and Plugins"
      },
      {
        "product": "Google Tag Manager",
        "vendor": "Google LLC",
        "category": "Tag Management",
        "categoryParent": "Intelligence and Analytics"
      },
      {
        "product": "Cloudflare CDN",
        "vendor": "Cloudflare, Inc.",
        "category": "Content Delivery Networks",
        "categoryParent": "IT Infrastructure"
      },
      {
        "product": "Cloudflare Website Optimization",
        "vendor": "Cloudflare, Inc.",
        "category": "Web Accelerators",
        "categoryParent": "IT Infrastructure"
      }
    ],
    "from_cache": false
  },
  "contacts": {
    "success": false,
    "company_name": "Baumer Electric AG",
    "segment": "unknown",
    "country": "Czech Republic",
    "contacts_found": 0,
    "contacts": [],
    "from_cache": false
  },
  "research_timestamp": "2026-04-23 15:08"
}