{
  "company_key": "hm systems a/s",
  "company_name": "HM Systems A/S",
  "domain": "",
  "domain_url": "",
  "events": "",
  "event_count": 1,
  "lead_class": "",
  "matched_account_id": null,
  "enrichment": {
    "company_name": "HM Systems A/S",
    "opportunity_score": 14,
    "estimated_deal_eur": 2200,
    "primary_segment": "unknown",
    "size_tier": "small",
    "timing_signals": [],
    "fit_score": 0.2,
    "component_scores": {
      "size": 0.3,
      "revenue": 0.2,
      "nace_fit": 0.2,
      "event_relevance": 0.25,
      "signals": 0.0,
      "client_bonus": 0.0
    }
  },
  "website_data": {},
  "technographics": {
    "success": true,
    "company": "HM Systems A/S",
    "autodesk_products": [],
    "competitor_products": [],
    "cad_bim_other": [],
    "total_technologies": 75,
    "all_technologies": [
      {
        "product": "Clifton Strengths",
        "vendor": "Gallup",
        "category": "Other Human Resources Software",
        "categoryParent": "Human Resources"
      },
      {
        "product": "Facebook Signal",
        "vendor": "Facebook, Inc.",
        "category": "Other Vertical Industries Software",
        "categoryParent": "Vertical Industries"
      },
      {
        "product": "Productiv",
        "vendor": "Productiv, Inc",
        "category": "Other IT Infrastructure Software",
        "categoryParent": "IT Infrastructure"
      },
      {
        "product": "Yoast",
        "vendor": "Yoast BV",
        "category": "Search Marketing",
        "categoryParent": "Marketing"
      },
      {
        "product": "Quali",
        "vendor": "QualiSystems Ltd.",
        "category": "Infrastructures as a Service",
        "categoryParent": "IT Infrastructure"
      },
      {
        "product": "Cloudflare",
        "vendor": "Cloudflare, Inc.",
        "category": "Other IT Infrastructure Software",
        "categoryParent": "IT Infrastructure"
      },
      {
        "product": "UseProof",
        "vendor": "Proof Technologies",
        "category": "Other Marketing Software",
        "categoryParent": "Marketing"
      },
      {
        "product": "Microsoft Outlook",
        "vendor": "Microsoft Corporation",
        "category": "Other Communication and Collaboration Software",
        "categoryParent": "Communication and Collaboration"
      },
      {
        "product": "HTML",
        "vendor": "WHATWG",
        "category": "Programming Languages",
        "categoryParent": "Programming"
      },
      {
        "product": "Google API",
        "vendor": "Google LLC",
        "category": "API Management",
        "categoryParent": "Data Management"
      },
      {
        "product": "CSS",
        "vendor": "World Wide Web Consortium",
        "category": "Programming Languages",
        "categoryParent": "Programming"
      },
      {
        "product": "goo.gl",
        "vendor": "Google LLC",
        "category": "URL Shorteners",
        "categoryParent": "Marketing"
      },
      {
        "product": "InMotion Hosting",
        "vendor": "InMotion Hosting Inc",
        "category": "Web Hosting",
        "categoryParent": "IT Infrastructure"
      },
      {
        "product": "Twitter Cards",
        "vendor": "Twitter, Inc.",
        "category": "Other Marketing Software",
        "categoryParent": "Marketing"
      },
      {
        "product": "jQuery",
        "vendor": "The jQuery Foundation Inc",
        "category": "Frameworks and Libraries",
        "categoryParent": "Programming"
      },
      {
        "product": "Microsoft Excel",
        "vendor": "Microsoft Corporation",
        "category": "Other Communication and Collaboration Software",
        "categoryParent": "Communication and Collaboration"
      },
      {
        "product": "Underscore.js",
        "vendor": "Underscore.js",
        "category": "Frameworks and Libraries",
        "categoryParent": "Programming"
      },
      {
        "product": "jQuery Migrate",
        "vendor": "The jQuery Foundation Inc",
        "category": "Frameworks and Libraries",
        "categoryParent": "Programming"
      },
      {
        "product": "Yoast SEO",
        "vendor": "Yoast BV",
        "category": "Search Marketing",
        "categoryParent": "Marketing"
      },
      {
        "product": "WPForms",
        "vendor": "WPForms LLC",
        "category": "Online Form Builders",
        "categoryParent": "Web Tools and Plugins"
      },
      {
        "product": "Google Global Site Tag",
        "vendor": "Google LLC",
        "category": "Web Analytics",
        "categoryParent": "Intelligence and Analytics"
      },
      {
        "product": "LinkedIn Recruiter",
        "vendor": "LinkedIn Corporation",
        "category": "Applicant Tracking Systems",
        "categoryParent": "Human Resources"
      },
      {
        "product": "iStock",
        "vendor": "Getty Images, Inc",
        "category": "Stock Images Providers",
        "categoryParent": "Audio, Video, Graphics"
      },
      {
        "product": "Daily",
        "vendor": "Daily.co.uk",
        "category": "Web Hosting",
        "categoryParent": "IT Infrastructure"
      },
      {
        "product": "Font Awesome",
        "vendor": "Fonticons, Inc.",
        "category": "Other Web Tools and Plugins",
        "categoryParent": "Web Tools and Plugins"
      },
      {
        "product": "Microsoft 365",
        "vendor": "Microsoft Corporation",
        "category": "Office Suites",
        "categoryParent": "Communication and Collaboration"
      },
      {
        "product": "Facebook Workplace",
        "vendor": "Facebook, Inc.",
        "category": "Team Collaboration",
        "categoryParent": "Communication and Collaboration"
      },
      {
        "product": "Microsoft Dynamics GP",
        "vendor": "Microsoft Corporation",
        "category": "Enterprise Resource Planning",
        "categoryParent": "Operations"
      },
      {
        "product": "Microsoft Dynamics",
        "vendor": "Microsoft Corporation",
        "category": "Enterprise Resource Planning",
        "categoryParent": "Operations"
      },
      {
        "product": "LinkedIn Sales Navigator",
        "vendor": "LinkedIn Corporation",
        "category": "Sales Intelligence",
        "categoryParent": "Sales"
      },
      {
        "product": "Connectifier",
        "vendor": "LinkedIn Corporation",
        "category": "Applicant Tracking Systems",
        "categoryParent": "Human Resources"
      },
      {
        "product": "Microsoft (common)",
        "vendor": "Microsoft Corporation",
        "category": "Miscellaneous",
        "categoryParent": "Miscellaneous"
      },
      {
        "product": "Lynda Business",
        "vendor": "LinkedIn Corporation",
        "category": "Corporate Learning Management Systems",
        "categoryParent": "Human Resources"
      },
      {
        "product": "Hotjar",
        "vendor": "Hotjar Ltd.",
        "category": "Web Analytics",
        "categoryParent": "Intelligence and Analytics"
      },
      {
        "product": "Shutterstock",
        "vendor": "Shutterstock, Inc.",
        "category": "Stock Images Providers",
        "categoryParent": "Audio, Video, Graphics"
      },
      {
        "product": "Applicant Pro",
        "vendor": "JobMatch LLC",
        "category": "Applicant Tracking Systems",
        "categoryParent": "Human Resources"
      },
      {
        "product": "CallRail",
        "vendor": "CallRail Inc.",
        "category": "Call Tracking",
        "categoryParent": "Marketing"
      },
      {
        "product": "LinkedIn Login",
        "vendor": "LinkedIn Corporation",
        "category": "Social Login",
        "categoryParent": "Web Tools and Plugins"
      },
      {
        "product": "Linkedin JavaScript SDK",
        "vendor": "LinkedIn Corporation",
        "category": "Social Login",
        "categoryParent": "Web Tools and Plugins"
      },
      {
        "product": "Google Universal Analytics",
        "vendor": "Google LLC",
        "category": "Web Analytics",
        "categoryParent": "Intelligence and Analytics"
      },
      {
        "product": "DialogTech",
        "vendor": "DialogTech, Inc.",
        "category": "Call Tracking",
        "categoryParent": "Marketing"
      },
      {
        "product": "CAPTCHA (common)",
        "vendor": "",
        "category": "CAPTCHA",
        "categoryParent": "Web Tools and Plugins"
      },
      {
        "product": "PHP",
        "vendor": "PHP Group",
        "category": "Programming Languages",
        "categoryParent": "Programming"
      },
      {
        "product": "reCAPTCHA",
        "vendor": "Google LLC",
        "category": "CAPTCHA",
        "categoryParent": "Web Tools and Plugins"
      },
      {
        "product": "Facebook Pixel",
        "vendor": "Facebook, Inc.",
        "category": "Other Advertising Software",
        "categoryParent": "Advertising"
      },
      {
        "product": "Facebook Web Custom Audiences",
        "vendor": "Facebook, Inc.",
        "category": "Retargeting",
        "categoryParent": "Advertising"
      },
      {
        "product": "Microsoft Exchange Online",
        "vendor": "Microsoft Corporation",
        "category": "Email Hosting",
        "categoryParent": "IT Infrastructure"
      },
      {
        "product": "Adobe Experience Manager",
        "vendor": "Adobe Inc.",
        "category": "Web Content Management Systems",
        "categoryParent": "Web Tools and Plugins"
      },
      {
        "product": "DoubleClick Floodlight",
        "vendor": "Google LLC",
        "category": "Tag Management",
        "categoryParent": "Intelligence and Analytics"
      },
      {
        "product": "Adobe Target",
        "vendor": "Adobe Inc.",
        "category": "A/B Testing",
        "categoryParent": "Intelligence and Analytics"
      }
    ],
    "from_cache": false
  },
  "contacts": {
    "success": false,
    "company_name": "HM Systems A/S",
    "segment": "unknown",
    "country": "Czech Republic",
    "contacts_found": 0,
    "contacts": [],
    "from_cache": false
  },
  "research_timestamp": "2026-04-23 12:47"
}