{
  "company_key": "lachem s.r.o.",
  "company_name": "LACHEM s.r.o.",
  "domain": "www.aliacem.cz",
  "domain_url": "https://www.aliacem.cz",
  "events": "MSV 2025 Full Exhibitor List",
  "event_count": 1,
  "lead_class": "whitespace",
  "matched_account_id": null,
  "enrichment": {
    "company_name": "LACHEM s.r.o.",
    "opportunity_score": 29,
    "estimated_deal_eur": 4200,
    "primary_segment": "AEC",
    "size_tier": "small",
    "timing_signals": [],
    "fit_score": 0.44,
    "component_scores": {
      "size": 0.3,
      "revenue": 0.2,
      "nace_fit": 0.44,
      "event_relevance": 0.25,
      "signals": 0.0,
      "client_bonus": 0.5
    },
    "ares_done": true,
    "ico": "03877418",
    "official_name": "LACHEM s.r.o.",
    "legal_form": "112",
    "nace_codes": [
      "461",
      "00",
      "G",
      "68200",
      "77220",
      "00",
      "461",
      "6820",
      "77290",
      "G"
    ],
    "ares_segments": [
      "AEC"
    ],
    "ares_primary_segment": "AEC",
    "ares_address": "Dobrovského 252, Žichlínské Předměstí, 56301 Lanškroun, Lanškroun, Dobrovského, 56301",
    "is_client": true,
    "current_products": "AutoCAD LT | PDMC",
    "total_seats": "15",
    "current_acv_eur": "33400.0",
    "potential_acv_eur": "50400.0",
    "nearest_renewal": "2026-05-17",
    "days_to_renewal": "24",
    "top_upsell": "AEC Collection",
    "top_upsell_reason": "Bundle with Revit, Civil 3D, Navisworks for full AEC workflow",
    "all_upsells": "AEC Collection; AutoCAD (full); Fusion Mfg Ext",
    "reseller": "ADEON CZ, s.r.o.",
    "maturity_label": "Collection",
    "industry_segment": "Engineering Service Providers",
    "ml_domain": "www.aliacem.cz",
    "zi_done": true,
    "zi_error": "No company found",
    "kurzy_done": true,
    "or_done": true,
    "leadership_change": false
  },
  "website_data": {
    "success": true,
    "domain": "https://www.aliacem.cz",
    "homepage": {
      "title": "Aliacem s.r.o.",
      "description": "Aliacem - kompletní projekční a inženýrské služby v oblasti zpracovávání surovin",
      "text_excerpt": "Aliacem s.r.o.\nOd návrhu po realizaci\nNabízíme kompletní projekční a inženýrské služby v oblasti výroby a zpracování cementu\nZobrazit více\nOd návrhu po realizaci\nNabízíme kompletní projekční a inženýrské služby v oblasti zpracovávání surovin\nZobrazit více\nNaše hlavní aktivity\nStudie proveditelnosti\nProjekční služby\nInvestiční výstavba\nEngineering & Řízení projektů\nZ projektů vybíráme\nChladič slínku\nInvestor:\nHolcim ÖSTERREICH\nMísto:\nMannersdorf am Leithagebirge\nRealizace:\n09/2024 - 04/2025\nSkladování slínku\nInvestor:\nHolcim Česko\nMísto:\nČížkovice\nRealizace:\n02.2022 - 11.2023\nRekonstrukce horních stupňů výměníku tepla\nInvestor:\nCement Hranice a.s.\nMísto:\nHranice na Moravě\nRealizace:\n10.2023 - 03.2024\nVýstavba sila bypass\nInvestor:\nZVVZ Milevsko a.s.\nMísto:\nHranice na Moravě\nRealizace:\n11.2013 - 03.2014\nRekonstrukce terciálního potrubí\nInvestor:\nCement Hranice a.s.\nMísto:\nHranice na Moravě\nRealizace:\n12.02.2019\nChladič cementu CHC 3000\nInvestor:\nCement Hranice a.s.\nMísto:\nHranice na Moravě\nRealizace:\n12.04.2019\nVšechny reference\nKdo jsme?\nJsme rodinná firma, která od roku 2007 poskytuje kompletní projekční a inženýrské služby – od prvotních návrhů po uvedení do provozu nejen v České republice, ale i v zahraničí.\nNaše silné stránky při realizaci projektů\nOdbornost\nIndividuální přístup\nFlexibilita\nInovativnost\nVíce o NÁS\nAktuálně z\nLinkedIn"
    },
    "about": {
      "url": "https://www.aliacem.cz/o-nas",
      "text": "O nás | Aliacem s.r.o.\nO nás\nRodinné hodnoty a osobní přístup\nJsme rodinná firma se sídlem v Přerově, která od roku 2007 poskytuje špičková řešení v oblasti výroby a zpracování cementu. Díky menšímu rodinnému prostředí klademe důraz na osobní přístup a flexibilitu. Přizpůsobujeme se jedinečným potřebám každého zákazníka a budujeme dlouhodobé vztahy založené na důvěře a transparentní komunikaci.\nNaše odborné služby od návrhu po realizaci\nSpecializujeme se na komplexní realizaci projektů – od úvodních návrhů a technicko-ekonomických studií přes přípravu projektové dokumentace až po výstavbu, spuštění provozu a zaškolení obsluhy. Naše řešení jsou inovativní, reflektují moderní technologie a trendy a přinášejí reálnou hodnotu.\n15 let zkušeností ve světě cementu\nBěhem více než 15 let jsme se podíleli na významných projektoch u nás i v zahraničí. Naše dlouholeté zkušenosti nám umožňují navrhovat efektivní a spolehlivá technologická řešení na míru, která vždy odpovídají představám klientů.\nProč právě my?\nOdbornost, individuální přístup, flexibilita a inovativnost jsou pilíře, na kterých stavíme každý náš projekt. Společně vytvoříme řešení, které splní vaše očekávání a nepřekročí rozpočet projektu."
    },
    "products": {
      "url": "https://www.aliacem.cz/sluzby",
      "text": "Služby | Aliacem s.r.o.\nSlužby\nKomplexní řešení pro cementárenský průmysl\nV Aliacem s.r.o. poskytujeme komplexní řešení pokrývající všechny fáze projektů v cementárenském průmyslu. Od úvodního návrhu po finální realizaci dbáme na nejvyšší standardy kvality, bezpečnosti a efektivity. Naše služby jsou navrženy tak, aby reflektovaly specifické potřeby klientů a přinášely hmatatelné výsledky v podobě efektivnější výroby a vyšší hodnoty jejich investic.\nZkušený tým odborníků a prověření partneři\nDisponujeme vlastním týmem zkušených projektových manažerů a strojních a elektro projektantů a technologů, kteří zajišťují precizní přípravu a realizaci každého projektu. Spolupracujeme také s prověřenými externími partnery – od dodavatelů, výrobců a specialistů na bezpečnost práce a další klíčové oblasti, abychom zajistili bezproblémový průběh a dokončení projektů.\nCo nabízíme?\nDůraz na dlouhodobou spolupráci\nVěříme, že úspěšné projekty stojí na transparentní komunikaci a pevných vztazích s našimi klienty. V Aliacem s.r.o. si dáváme za cíl vybudovat dlouhodobá partnerství. Proto není naším cílem jen úspěšně dokončit projekt, ale stát se také vašim spolehlivým partnerem, který bude připraven reagovat na vaše potřeby a spolupracovat s vámi na dalších projektech.\nInovace a odpovědnost na prvním místě\nNaše řešení zohledňují aktuální trendy v cementárenském průmyslu, inovativní technologie a environmentální odpovědnost. Aktivně se účastníme mezinárodních konferencí a sledujeme vývoj v oboru, abychom mohli klientům nabídnout to nejlepší. S Aliacem s.r.o. získáte spolehlivého partnera, který zrealizuje vaše projekty podle plánu.\nStudie proveditelnosti\nTechnická analýza\nEkonomické vyhodnocení\nČasový plán realizace\nProjekční služby\nDokumentace pro územní řízení\nDokumentace pro stavební povolení\nProváděcí dokumentace\nVýrobní dokumentace\nInvestiční výstavba\nZajištění výroby a nákupu technologie\nZajištění výstavby\nUvedení do provozu\nEngineering a řízení projektů\nProjektové řízení výstavby\nSupervize stavebních a montážních prací\nptimalizace provozu zařízení\nPo záruční servis\nak to u nás probíhá?\nKaždý projekt začínáme pečlivým návrhem, kde společně s vámi definujeme řešení na míru vašim potřebám. Následuje precizní realizace, při které se staráme o každý detail, aby vše odpovídalo plánu. Nakonec uvedeme technologii do provozu, zaškolíme obsluhu a zajistíme, že vše funguje spolehlivě a efektivně. Stručně řečeno, jsme tady pro vás od návrhu po uvedení do provozu."
    },
    "contact_page": {
      "url": "https://www.aliacem.cz/kontakty",
      "text": "Kontakty | Aliacem s.r.o.\nKontakty\nKontaktní osoby\nIng. Milan Paštěka\nJednatel\nmilanpasteka@aliacem.cz\nIng. Petr Paštěka\nJednatel\npetrpasteka@aliacem.cz\nSpolečnosti\nALIACEM s.r.o.\n9. května 3303/119\n750 02 Přerov\nČeská republika\nobchod@aliacem.cz\n+420 607 137 074\nIČO: 27813606\nDIČ: CZ27813606\nIdentifikátor datové schránky: qn9kn96\nSpolečnost s ručením omezeným;\nKrajský soud v Ostravě, odd. C vložka 52539\nMapa\nACM INV a.s.\nK Moštěnici 188/3,\nPřerov VI-Újezdec,\n750 02 Přerov\nČeská republika\nIČO: 23109726\nACM Nemovitosti s.r.o.\nK Moštěnici 188/3,\nPřerov VI-Újezdec,\n750 02 Přerov\nČeská republika\nIČO: 22525432"
    }
  },
  "technographics": {
    "success": true,
    "company": "LACHEM s.r.o.",
    "autodesk_products": [],
    "competitor_products": [],
    "cad_bim_other": [],
    "total_technologies": 10,
    "all_technologies": [
      {
        "product": "Google Hosted Libraries",
        "vendor": "Google LLC",
        "category": "Content Delivery Networks",
        "categoryParent": "IT Infrastructure"
      },
      {
        "product": "CSS",
        "vendor": "World Wide Web Consortium",
        "category": "Programming Languages",
        "categoryParent": "Programming"
      },
      {
        "product": "Twitter Cards",
        "vendor": "Twitter, Inc.",
        "category": "Other Marketing Software",
        "categoryParent": "Marketing"
      },
      {
        "product": "jQuery",
        "vendor": "The jQuery Foundation Inc",
        "category": "Frameworks and Libraries",
        "categoryParent": "Programming"
      },
      {
        "product": "fancyBox",
        "vendor": "fancyapps",
        "category": "Frameworks and Libraries",
        "categoryParent": "Programming"
      },
      {
        "product": "Microsoft 365",
        "vendor": "Microsoft Corporation",
        "category": "Office Suites",
        "categoryParent": "Communication and Collaboration"
      },
      {
        "product": "Google Maps API",
        "vendor": "Google LLC",
        "category": "Mapping and GIS",
        "categoryParent": "Web Tools and Plugins"
      },
      {
        "product": "Slimbox",
        "vendor": "",
        "category": "Frameworks and Libraries",
        "categoryParent": "Programming"
      },
      {
        "product": "Microsoft Exchange Online",
        "vendor": "Microsoft Corporation",
        "category": "Email Hosting",
        "categoryParent": "IT Infrastructure"
      },
      {
        "product": "nginx",
        "vendor": "nginx.org by Nginx, Inc.",
        "category": "Web and Application Servers",
        "categoryParent": "IT Infrastructure"
      }
    ],
    "from_cache": false
  },
  "contacts": {
    "success": true,
    "company_name": "LACHEM s.r.o.",
    "segment": "AEC",
    "country": "Czech Republic",
    "contacts_found": 4,
    "contacts": [
      {
        "first_name": "Michal",
        "last_name": "Paštěka",
        "title": "Project Manager",
        "email": "michalpasteka@aliacem.cz",
        "phone": "",
        "company": "Aliacem",
        "country": "Czech Republic",
        "has_email": true,
        "has_phone": false,
        "accuracy_score": 97.0
      },
      {
        "first_name": "Jaroslav",
        "last_name": "Oslanec",
        "title": "Senior Project Designer",
        "email": "jaroslavoslanec@aliacem.cz",
        "phone": "",
        "company": "Aliacem",
        "country": "Czech Republic",
        "has_email": true,
        "has_phone": false,
        "accuracy_score": 98.0
      },
      {
        "first_name": "Miroslav",
        "last_name": "Gašpařík",
        "title": "Projektant",
        "email": "miroslavgasparik@aliacem.cz",
        "phone": "",
        "company": "Aliacem",
        "country": "Czech Republic",
        "has_email": true,
        "has_phone": false,
        "accuracy_score": 85.0
      },
      {
        "first_name": "Jakub",
        "last_name": "Nevrlý",
        "title": "Projektant",
        "email": "jakubnevrly@aliacem.cz",
        "phone": "",
        "company": "Aliacem",
        "country": "Czech Republic",
        "has_email": true,
        "has_phone": false,
        "accuracy_score": 83.0
      }
    ],
    "from_cache": false,
    "contacts_cleaned": true,
    "removed_non_czech": 1
  },
  "research_timestamp": "2026-04-23 12:59"
}