{
  "company_key": "pewag austria gmbh",
  "company_name": "pewag austria GmbH",
  "domain": "www.pewag.com",
  "domain_url": "https://www.pewag.com",
  "events": "MSV 2025 Full Exhibitor List",
  "event_count": 1,
  "lead_class": "new_market",
  "matched_account_id": null,
  "enrichment": {
    "company_name": "pewag austria GmbH",
    "opportunity_score": 14,
    "estimated_deal_eur": 2200,
    "primary_segment": "unknown",
    "size_tier": "small",
    "timing_signals": [],
    "fit_score": 0.2,
    "component_scores": {
      "size": 0.3,
      "revenue": 0.2,
      "nace_fit": 0.2,
      "event_relevance": 0.25,
      "signals": 0.0,
      "client_bonus": 0.0
    },
    "ares_done": true,
    "ares_error": "Not found in ARES",
    "zi_done": true,
    "employee_count": 1650,
    "revenue": 448092,
    "zi_company_name": "PEWAG CHAIN",
    "zi_domain": "www.pewag.com",
    "zi_city": "Klagenfurt am Wörthersee",
    "zi_country": "Austria",
    "zi_industry": "",
    "zi_sub_industry": ""
  },
  "website_data": {
    "success": true,
    "domain": "https://www.pewag.com",
    "homepage": {
      "title": "Homepage - pewag",
      "description": "",
      "text_excerpt": "Homepage - pewag\nProducts\nProducts\nLIFTING SOLUTIONS\nG10\nG12\nFire Resistant Systems\nInox - Stainless Steel Lifting Systems\nlevo\nLifting Beams\nLifting Clamps\nLifting Magnets\npro points\nOffshore\nShackles\nTextile\nWire Rope Fittings\nChain Cutter\nSNOW CHAINS\nPassenger Car & SUV\nBus & Commercial Vehicles\nOff-road Vehicles & Tractors\nSpecial Vehicles\nExcavators\nSpare Parts\nFORESTRY TECHNIQUE\nForestry Chains\nForestry Tracks\nSpare Parts\nHarvester Bars & Chains\nSHOP\nCONVEYOR SYSTEMS & HOIST CHAINS\nConveyor Chains\nConnection Links\nAttachments for Conveyor Systems\nWheels & Sprockets\nHoist Chains\nTransmission Chains\nRoller Chains & Sprockets\nDO IT YOURSELF PRODUCTS\nChains\nWires & Ropes\nAccessories\nNails\nTextile Lifting & Lashing Equipment\nForestry Chain Applications\nLashing Applications\nTYRE PROTECTION CHAINS\nOpen Pit Mining\nUnderground Mining & Tunneling\nQuarrying\nSlag & Scrap Handling\nAccessories & Spare Parts\nDigital Services\nDigital Services\ndigital Services\nSnow Chain Configurator - Corporate Customers\nSnow Chain Configurator - Private Customers\nChain Sling Configurator\nClamp Advisor\npro points Advisor\npeTAG Software Solution\nLifting Beam Configurator\nFind Forestry Products\npewag academy\nCatalogs\nCertificates\npewag academy\nNews\nSolutions\nSolutions\nSolutions\nSnow Chains\nForestry Technique\nLifting Solutions\nConveyor Systems & Hoist Chains\nTire Protection Chains\nDo It Yourself Products\nEngineering Solutions\nindustries\nAgriculture & Forestry\nAquaculture, Fisheries & Marine\nConstruction\nEngineering & Manufacturing\nMining\nMoulding\nOil & Gas\nPublic Administration\nTransport & Logistics\nVehicles & Road Traffic\nWaste Water\nWind Energy\nCorporate Certificates\nCustomer Service\nNews\nInnovation\nAbout pewag\nAbout pewag\ncompany\nAbout Us\nTradition & Innovation\nSustainability\nNews\ncareerS\nWorking at pewag\nJobs\ncontact\nLocations and Partners\nCustomer Service\nCareers at pewag\nCart\nInternational (EN)\nInternational\nInternational (EN)\nAmericas\nBrazil (PT)\nCanada (EN)\nColombia (ES)\nMexico (ES)\nUSA (EN)\nAsia & Oceania\nAustralia (EN)\nIndia (EN)\nEurope\nAustria (DE)\nCzech Republic (CZ)\nFinland (FI)\nFrance (FR)\nGermany (DE)\nItaly (IT)\nNetherlands (NL)\nNorway (NO)\nPoland (PL)\nPortugal (PT)\nRomania (RO)\nSlovakia (SK)\nSweden (SV)\nSwitzerland (DE)\nUkraine (UA)\nUnited Kingdom (EN)\nRegion\nInternational\nInternational (EN)\nAmericas\nBrazil (PT)\nCanada (EN)\nColombia (ES)\nMexico (ES)\nUSA (EN)\nAsia & Oceania\nAustralia (EN)\nIndia (EN)\nEurope\nAustria (DE)\nCzech Republic (CZ)\nFinland (FI)\nFrance (FR)\nGermany (DE)\nItaly (IT)\nNetherlands (NL)\nNorway (NO)\nPoland (PL)\nPortugal (PT)\nRomania (RO)\nSlovakia (SK)\nSweden (SV)\nSwitzerland (DE)\nUkraine (UA)\nUnited Kingdom (EN)\nSAFETY IN MOVING PEOPLE & GOODS\nstrong is not enough.\nSnow\nChains\nForestry\nTechnique\nLifting\nSolutions\nConveyor\nSystems & Hoist\nChains\nTire Protection\nChains\nDo It Yourself\nProducts\nEngineering\nSolutions\nSnow\nChains\nForestry\nTechnique\nLifting\nSolutions\nConveyor\nSystems & Hoist\nChains\nTire Protection\nChains\nDo It Yourself\nProducts\nEnginee"
    },
    "about": {
      "url": "https://www.pewag.com/o-nas",
      "text": "About us - pewag\nProducts\nProducts\nLIFTING SOLUTIONS\nG10\nG12\nFire Resistant Systems\nInox - Stainless Steel Lifting Systems\nlevo\nLifting Beams\nLifting Clamps\nLifting Magnets\npro points\nOffshore\nShackles\nTextile\nWire Rope Fittings\nChain Cutter\nSNOW CHAINS\nPassenger Car & SUV\nBus & Commercial Vehicles\nOff-road Vehicles & Tractors\nSpecial Vehicles\nExcavators\nSpare Parts\nFORESTRY TECHNIQUE\nForestry Chains\nForestry Tracks\nSpare Parts\nHarvester Bars & Chains\nSHOP\nCONVEYOR SYSTEMS & HOIST CHAINS\nConveyor Chains\nConnection Links\nAttachments for Conveyor Systems\nWheels & Sprockets\nHoist Chains\nTransmission Chains\nRoller Chains & Sprockets\nDO IT YOURSELF PRODUCTS\nChains\nWires & Ropes\nAccessories\nNails\nTextile Lifting & Lashing Equipment\nForestry Chain Applications\nLashing Applications\nTYRE PROTECTION CHAINS\nOpen Pit Mining\nUnderground Mining & Tunneling\nQuarrying\nSlag & Scrap Handling\nAccessories & Spare Parts\nDigital Services\nDigital Services\ndigital Services\nSnow Chain Configurator - Corporate Customers\nSnow Chain Configurator - Private Customers\nChain Sling Configurator\nClamp Advisor\npro points Advisor\npeTAG Software Solution\nLifting Beam Configurator\nFind Forestry Products\npewag academy\nCatalogs\nCertificates\npewag academy\nNews\nSolutions\nSolutions\nSolutions\nSnow Chains\nForestry Technique\nLifting Solutions\nConveyor Systems & Hoist Chains\nTire Protection Chains\nDo It Yourself Products\nEngineering Solutions\nindustries\nAgriculture & Forestry\nAquaculture, Fisheries & Marine\nConstruction\nEngineering & Manufacturing\nMining\nMoulding\nOil & Gas\nPublic Administration\nTransport & Logistics\nVehicles & Road Traffic\nWaste Water\nWind Energy\nCorporate Certificates\nCustomer Service\nNews\nInnovation\nAbout pewag\nAbout pewag\ncompany\nAbout Us\nTradition & Innovation\nSustainability\nNews\ncareerS\nWorking at pewag\nJobs\ncontact\nLocations and Partners\nCustomer Service\nCareers at pewag\nCart\nInternational (EN)\nInternational\nInternational (EN)\nAmericas\nBrazil (PT)\nCanada (EN)\nColombia (ES)\nMexico (ES)\nUSA (EN)\nAsia & Oceania\nAustralia (EN)\nIndia (EN)\nEurope\nAustria (DE)\nCzech Republic (CZ)\nFinland (FI)\nFrance (FR)\nGermany (DE)\nItaly (IT)\nNetherlands (NL)\nNorway (NO)\nPoland (PL)\nPortugal (PT)\nRomania (RO)\nSlovakia (SK)\nSweden (SV)\nSwitzerland (DE)\nUkraine (UA)\nUnited Kingdom (EN)\nRegion\nInternational\nInternational (EN)\nAmericas\nBrazil (PT)\nCanada (EN)\nColombia (ES)\nMexico (ES)\nUSA (EN)\nAsia & Oceania\nAustralia (EN)\nIndia (EN)\nEurope\nAustria (DE)\nCzech Republic (CZ)\nFinland (FI)\nFrance (FR)\nGermany (DE)\nItaly (IT)\nNetherlands (NL)\nNorway (NO)\nPoland (PL)\nPortugal (PT)\nRomania (RO)\nSlovakia (SK)\nSweden (SV)\nSwitzerland (DE)\nUkraine (UA)\nUnited Kingdom (EN)\nHome\nAbout us\nABOUT US\nBuilt to Last. Here to Stay.\nInnovative since 1479\nAt pewag, we honor our rich history while committing ourselves to a future of safety, reliability and innovation. For over 500 years, we have provided our customers with world-class chain solutions that are both strong and sustainable. Our expertise combines traditional craftsmanship with cutting-edge technology to ensure our products exceed the demands of a changing world.\nCommitted to Quality\nWe empower our customers around the globe to move people and goods with confidence and safety. In industries that demand the highest standards of performance, safety and efficiency, we are a trusted partner. Through our commitment to green energy and continuous innovation, we create forward-thinking, lasting value.\nISO Certificates\nWe Are Part of pewag group\nFrom a modest 15th-century forge, we have evolved into a forward-thinking global group. Our goal is carbon-neutral production by 2030. The pewag group supports over 15 multinational brands, providing a solid foundation and shared values for employees and stakeholders. With more than 50 locations on five continents, we form a global network of specialists, partners, and suppliers, strengthened by external experts in science, research, and development.\nDiscover pewag group\nCorporate Values\nCareers at pe"
    },
    "products": {
      "url": "https://www.pewag.com/products",
      "text": "B2B catalog\nClose menu\nCategories\nLIFTING SOLUTIONS\nDO IT YOURSELF PRODUCTS\nSNOW CHAINS\nFORESTRY TECHNIQUE\nCONVEYOR SYSTEMS & HOIST CHAINS\nTYRE PROTECTION CHAINS\nCart\nProfile\nChain Sling\nConfigurator\nStart\nSnow Chain\nConfigurator\nStart\npro points\nAdvisor\nStart\nLIFTING SOLUTIONS\nG10\nG12\nFire Resistant Systems\nInox - Stainless Steel Lifting Systems\nlevo\nLifting Beams\nShow all\nDO IT YOURSELF PRODUCTS\nChains\nWires & Ropes\nAccessories\nNails\nTextile Lifting & Lashing Equipment\nForestry Chain Applications\nShow all\nSNOW CHAINS\nPassenger Car & SUV\nBus & Commercial Vehicles\nOff-road Vehicles & Tractors\nSpecial Vehicles\nExcavators\nSpare Parts\nShow all\nFORESTRY TECHNIQUE\nForestry Chains\nForestry Tracks\nSpare Parts\nHarvester Bars & Chains\nShow all\nCONVEYOR SYSTEMS & HOIST CHAINS\nConveyor Chains\nConnection Links\nAttachments for Conveyor Systems\nWheels & Sprockets\nHoist Chains\nTransmission Chains\nShow all\nTYRE PROTECTION CHAINS\nOpen Pit Mining\nUnderground Mining & Tunneling\nQuarrying\nSlag & Scrap Handling\nAccessories & Spare Parts\nShow all\nTradition & Innovation\nAt pewag, we honor our rich history while committing ourselves to a future of safety, reliability and innovation. For over 500 years, we have provided our customers with world-class chain solutions that are both strong and sustainable. Our expertise combines traditional craftsmanship with cutting-edge technology to ensure our products exceed the demands of a changing world.\nInnovation for a sustainable future\nFor us at pewag and the entire pewag group, sustainability is not just an ambition or a trend. It's a responsibility. Since our beginnings in the 15th century, we have evolved into a global leader committed to achieving carbon-neutral production by 2030, in line with the Paris Agreement and EU Climate Law. Our initiatives include renewable energy, resource conservation, social responsibility and ethical business practices. From generating clean energy and recycling the vast majority of our waste (83% by 2023) to promoting health, safety and good working conditions throughout our value chain, we are pushing sustainable development.\nReliable Partner\nHigh Quality Materials\nGlobal Player\nCraft & Innovation\nSustainable Business Practices"
    },
    "contact_page": {}
  },
  "technographics": {
    "success": true,
    "company": "pewag austria GmbH",
    "autodesk_products": [],
    "competitor_products": [],
    "cad_bim_other": [
      "InVision"
    ],
    "total_technologies": 58,
    "all_technologies": [
      {
        "product": "Google Tag Manager",
        "vendor": "Google LLC",
        "category": "Tag Management",
        "categoryParent": "Intelligence and Analytics"
      },
      {
        "product": "SAP",
        "vendor": "SAP SE",
        "category": "Enterprise Resource Planning",
        "categoryParent": "Operations"
      },
      {
        "product": "Operative",
        "vendor": "SintecMedia Ltd.",
        "category": "Other Advertising Software",
        "categoryParent": "Advertising"
      },
      {
        "product": "Google Global Site Tag",
        "vendor": "Google LLC",
        "category": "Web Analytics",
        "categoryParent": "Intelligence and Analytics"
      },
      {
        "product": "Microsoft",
        "vendor": "Microsoft Corporation",
        "category": "Other Intelligence and Analytics Software",
        "categoryParent": "Intelligence and Analytics"
      },
      {
        "product": "Udemy",
        "vendor": "Udemy, Inc.",
        "category": "Education Management",
        "categoryParent": "Vertical Industries"
      },
      {
        "product": "Expresshr",
        "vendor": "expressHR",
        "category": "Recruitment Marketing",
        "categoryParent": "Human Resources"
      },
      {
        "product": "Prove (formerly Payfone)",
        "vendor": "Prove",
        "category": "Other Security Software",
        "categoryParent": "Security"
      },
      {
        "product": "Yoast",
        "vendor": "Yoast BV",
        "category": "Search Marketing",
        "categoryParent": "Marketing"
      },
      {
        "product": "Quali",
        "vendor": "QualiSystems Ltd.",
        "category": "Infrastructures as a Service",
        "categoryParent": "IT Infrastructure"
      },
      {
        "product": "SelectLeaders",
        "vendor": "SelectLeaders",
        "category": "Job Boards",
        "categoryParent": "Human Resources"
      },
      {
        "product": "P2 Energy Solutions",
        "vendor": "P2 Energy Solutions",
        "category": "Enterprise Resource Planning",
        "categoryParent": "Operations"
      },
      {
        "product": "Nickelled",
        "vendor": "Nickelled Ltd",
        "category": "Other Customer Service Software",
        "categoryParent": "Customer Service"
      },
      {
        "product": "HTML",
        "vendor": "WHATWG",
        "category": "Programming Languages",
        "categoryParent": "Programming"
      },
      {
        "product": "Google API",
        "vendor": "Google LLC",
        "category": "API Management",
        "categoryParent": "Data Management"
      },
      {
        "product": "CSS",
        "vendor": "World Wide Web Consortium",
        "category": "Programming Languages",
        "categoryParent": "Programming"
      },
      {
        "product": "NTENT Hosting",
        "vendor": "NTENT Inc",
        "category": "Web Hosting",
        "categoryParent": "IT Infrastructure"
      },
      {
        "product": "Blitzen",
        "vendor": "Blitzen",
        "category": "Lead Generation",
        "categoryParent": "Sales"
      },
      {
        "product": "Adobe Creative Cloud",
        "vendor": "Adobe Inc.",
        "category": "Other Audio, Video, Graphics Software",
        "categoryParent": "Audio, Video, Graphics"
      },
      {
        "product": "Zingfit",
        "vendor": "ZINGFIT LLC",
        "category": "Appointment Scheduling",
        "categoryParent": "Sales"
      },
      {
        "product": "Gupy",
        "vendor": "Gupy",
        "category": "Applicant Tracking Systems",
        "categoryParent": "Human Resources"
      },
      {
        "product": "Teamwork",
        "vendor": "Teamwork.com, Ltd.",
        "category": "Other Communication and Collaboration Software",
        "categoryParent": "Communication and Collaboration"
      },
      {
        "product": "Twitter Cards",
        "vendor": "Twitter, Inc.",
        "category": "Other Marketing Software",
        "categoryParent": "Marketing"
      },
      {
        "product": "jQuery",
        "vendor": "The jQuery Foundation Inc",
        "category": "Frameworks and Libraries",
        "categoryParent": "Programming"
      },
      {
        "product": "Microsoft PowerPoint",
        "vendor": "Microsoft Corporation",
        "category": "Other Communication and Collaboration Software",
        "categoryParent": "Communication and Collaboration"
      },
      {
        "product": "Microsoft Excel",
        "vendor": "Microsoft Corporation",
        "category": "Other Communication and Collaboration Software",
        "categoryParent": "Communication and Collaboration"
      },
      {
        "product": "Yoast SEO",
        "vendor": "Yoast BV",
        "category": "Search Marketing",
        "categoryParent": "Marketing"
      },
      {
        "product": "CKEditor",
        "vendor": "CKSource sp. z.o.o. sp.k.",
        "category": "Other Programming Software",
        "categoryParent": "Programming"
      },
      {
        "product": "eSSential",
        "vendor": "eLogic Learning LLC",
        "category": "Corporate Learning Management Systems",
        "categoryParent": "Human Resources"
      },
      {
        "product": "Magento 1.7",
        "vendor": "Magento, Inc.",
        "category": "E-Commerce Platforms",
        "categoryParent": "E-Commerce"
      },
      {
        "product": "Issuu",
        "vendor": "Issuu, Inc.",
        "category": "Other Marketing Software",
        "categoryParent": "Marketing"
      },
      {
        "product": "jsDelivr",
        "vendor": "ProspectOne Inc",
        "category": "Content Delivery Networks",
        "categoryParent": "IT Infrastructure"
      },
      {
        "product": "InVision",
        "vendor": "InVisionApp Inc.",
        "category": "Computer Aided Design",
        "categoryParent": "Vertical Industries"
      },
      {
        "product": "Microsoft OneDrive",
        "vendor": "Microsoft Corporation",
        "category": "File Sharing",
        "categoryParent": "Communication and Collaboration"
      },
      {
        "product": "VMware",
        "vendor": "Broadcom Inc.",
        "category": "Platforms as a Service",
        "categoryParent": "IT Infrastructure"
      },
      {
        "product": "SentinelOne",
        "vendor": "SentinelOne, Inc.",
        "category": "Endpoint Protection",
        "categoryParent": "Security"
      },
      {
        "product": "Microsoft (common)",
        "vendor": "Microsoft Corporation",
        "category": "Miscellaneous",
        "categoryParent": "Miscellaneous"
      },
      {
        "product": "TeamViewer",
        "vendor": "TeamViewer GmbH",
        "category": "Other Customer Service Software",
        "categoryParent": "Customer Service"
      },
      {
        "product": "MySQL",
        "vendor": "Oracle Corporation",
        "category": "Databases",
        "categoryParent": "Data Management"
      },
      {
        "product": "Ausgezeichnet",
        "vendor": "AUBII GmbH",
        "category": "Online Review Management",
        "categoryParent": "Marketing"
      },
      {
        "product": "reCAPTCHA v2.0",
        "vendor": "Google LLC",
        "category": "CAPTCHA",
        "categoryParent": "Web Tools and Plugins"
      },
      {
        "product": "PetWise Marketing",
        "vendor": "AVImark",
        "category": "Healthcare Marketing",
        "categoryParent": "Vertical Industries"
      },
      {
        "product": "CAPTCHA (common)",
        "vendor": "",
        "category": "CAPTCHA",
        "categoryParent": "Web Tools and Plugins"
      },
      {
        "product": "PHP",
        "vendor": "PHP Group",
        "category": "Programming Languages",
        "categoryParent": "Programming"
      },
      {
        "product": "reCAPTCHA",
        "vendor": "Google LLC",
        "category": "CAPTCHA",
        "categoryParent": "Web Tools and Plugins"
      },
      {
        "product": "nginx",
        "vendor": "nginx.org by Nginx, Inc.",
        "category": "Web and Application Servers",
        "categoryParent": "IT Infrastructure"
      },
      {
        "product": "Adobe Commerce",
        "vendor": "Adobe Inc.",
        "category": "E-Commerce Platforms",
        "categoryParent": "E-Commerce"
      },
      {
        "product": "PayPal",
        "vendor": "PayPal Holdings, Inc.",
        "category": "Payment Processing",
        "categoryParent": "E-Commerce"
      },
      {
        "product": "Google Workspace",
        "vendor": "Google LLC",
        "category": "Office Suites",
        "categoryParent": "Communication and Collaboration"
      },
      {
        "product": "WordPress.com",
        "vendor": "Automattic Inc",
        "category": "Web Content Management Systems",
        "categoryParent": "Web Tools and Plugins"
      }
    ],
    "from_cache": false
  },
  "contacts": {
    "success": true,
    "company_name": "pewag austria GmbH",
    "segment": "unknown",
    "country": "Czech Republic",
    "contacts_found": 1,
    "contacts": [
      {
        "first_name": "Vishwanath",
        "last_name": "Orkala",
        "title": "Managing Director",
        "email": "ov@pewag.com",
        "phone": "",
        "company": "PEWAG CHAIN",
        "country": "",
        "has_email": true,
        "has_phone": false,
        "accuracy_score": 92.0
      }
    ],
    "from_cache": false,
    "contacts_cleaned": true,
    "removed_non_czech": 4
  },
  "research_timestamp": "2026-04-23 17:11"
}