{
  "company_key": "sar_mont_e",
  "company_name": "SAR Montáže",
  "domain": "",
  "events": "Digital Factory 2.0 / MSV 2026",
  "technographics": {
    "success": true,
    "company": "SAR Montáže",
    "autodesk_products": [],
    "competitor_products": [],
    "cad_bim_other": [],
    "total_technologies": 8,
    "all_technologies": [
      {
        "product": "CSS",
        "vendor": "World Wide Web Consortium",
        "category": "Programming Languages",
        "categoryParent": "Programming"
      },
      {
        "product": "Lightbox",
        "vendor": "Lokesh Dhakar",
        "category": "Other Web Tools and Plugins",
        "categoryParent": "Web Tools and Plugins"
      },
      {
        "product": "jQuery",
        "vendor": "The jQuery Foundation Inc",
        "category": "Frameworks and Libraries",
        "categoryParent": "Programming"
      },
      {
        "product": "CKEditor",
        "vendor": "CKSource sp. z.o.o. sp.k.",
        "category": "Other Programming Software",
        "categoryParent": "Programming"
      },
      {
        "product": "Google Maps API (free)",
        "vendor": "Google LLC",
        "category": "Mapping and GIS",
        "categoryParent": "Web Tools and Plugins"
      },
      {
        "product": "Google Maps API",
        "vendor": "Google LLC",
        "category": "Mapping and GIS",
        "categoryParent": "Web Tools and Plugins"
      },
      {
        "product": "Google Analytics",
        "vendor": "Google LLC",
        "category": "Web Analytics",
        "categoryParent": "Intelligence and Analytics"
      },
      {
        "product": "Drupal",
        "vendor": "Drupalcon, Inc.",
        "category": "Web Content Management Systems",
        "categoryParent": "Web Tools and Plugins"
      }
    ],
    "from_cache": false
  },
  "contacts": {
    "success": true,
    "contacts": [
      {
        "fullName": "ZDENĚK LIPOVÝ",
        "firstName": "ZDENĚK",
        "lastName": "LIPOVÝ",
        "jobTitle": "Managing Director (Jednatel)",
        "email": "",
        "phone": "",
        "linkedin": "",
        "source": "ares_vr"
      },
      {
        "fullName": "RADOMÍRA LIPOVÁ",
        "firstName": "RADOMÍRA",
        "lastName": "LIPOVÁ",
        "jobTitle": "Managing Director (Jednatel)",
        "email": "",
        "phone": "",
        "linkedin": "",
        "source": "ares_vr"
      }
    ],
    "total_found": 2,
    "sources_used": [
      "ares_vr"
    ]
  },
  "research_timestamp": "2026-04-24 17:40:57",
  "website_data": {
    "success": false,
    "domain": "https://www.sarcz.cz",
    "homepage": {},
    "about": {},
    "products": {},
    "contact_page": {}
  }
}