{
  "company_key": "seven, the energy efficiency center, z.ú.",
  "company_name": "SEVEn, The Energy Efficiency Center, z.ú.",
  "domain": "",
  "domain_url": "",
  "events": "Czech Green Building Council Members",
  "event_count": 1,
  "lead_class": "new_market",
  "matched_account_id": null,
  "enrichment": {
    "company_name": "SEVEn, The Energy Efficiency Center, z.ú.",
    "opportunity_score": 23,
    "estimated_deal_eur": 4200,
    "primary_segment": "AEC",
    "size_tier": "small",
    "timing_signals": [],
    "fit_score": 0.65,
    "component_scores": {
      "size": 0.3,
      "revenue": 0.2,
      "nace_fit": 0.65,
      "event_relevance": 0.25,
      "signals": 0.0,
      "client_bonus": 0.0
    },
    "ares_done": true,
    "ico": "05399416",
    "official_name": "SEVEn, The Energy Efficiency Center, z.ú.",
    "legal_form": "161",
    "nace_codes": [
      "71110",
      "71120",
      "00",
      "41000",
      "18200",
      "72",
      "00",
      "182",
      "7111",
      "72",
      "7112",
      "4120"
    ],
    "ares_segments": [
      "AEC"
    ],
    "ares_primary_segment": "AEC",
    "ares_address": "Americká 579/17, Vinohrady, 12000 Praha 2, Praha, Americká, 12000",
    "zi_done": true,
    "zi_error": "No company found",
    "kurzy_done": true,
    "or_done": true,
    "leadership_change": false
  },
  "website_data": {},
  "technographics": {
    "success": false,
    "error": "No company found"
  },
  "contacts": {
    "success": false,
    "company_name": "SEVEn, The Energy Efficiency Center, z.ú.",
    "segment": "AEC",
    "country": "Czech Republic",
    "contacts_found": 0,
    "contacts": [],
    "from_cache": false
  },
  "research_timestamp": "2026-04-23 15:24"
}